topsis_102003451/102003451.py
topsis_102003451-0.1.dist-info/METADATA
topsis_102003451-0.1.dist-info/WHEEL
topsis_102003451-0.1.dist-info/entry_points.txt
topsis_102003451-0.1.dist-info/top_level.txt
topsis_102003451-0.1.dist-info/RECORD
