Metadata-Version: 2.1
Name: topsis-102003451
Version: 0.1
Summary: This is package for topsis of version 0.3
Author: Riya
Author-email: rriya_be20@thapar.edu
Requires-Dist: pandas
